stactools/global_mangrove_watch/__init__.py
stactools/global_mangrove_watch/commands.py
stactools/global_mangrove_watch/constants.py
stactools/global_mangrove_watch/stac.py
stactools_global_mangrove_watch-0.2.3.dist-info/licenses/LICENSE
stactools_global_mangrove_watch-0.2.3.dist-info/METADATA
stactools_global_mangrove_watch-0.2.3.dist-info/WHEEL
stactools_global_mangrove_watch-0.2.3.dist-info/top_level.txt
stactools_global_mangrove_watch-0.2.3.dist-info/RECORD
