Metadata-Version: 2.4
Name: stactools-global-mangrove-watch
Version: 0.2.3
Summary: A stactools package for the Global Mangrove Watch dataset
Author-email: Henry Rodman <henry@developmentseed.org>
Maintainer-email: Henry Rodman <henry@developmentseed.org>
License: Apache-2.0
Project-URL: Github, https://github.com/stactools-packages/global-mangrove-watch
Project-URL: Issues, https://github.com/stactools-packages/global-mangrove-watch/issues
Keywords: stactools,pystac,catalog,STAC,mangrove
Classifier: Development Status :: 3 - Alpha
Classifier: Intended Audience :: Developers
Classifier: License :: OSI Approved :: Apache Software License
Classifier: Natural Language :: English
Classifier: Programming Language :: Python :: 3
Classifier: Programming Language :: Python :: 3.10
Classifier: Programming Language :: Python :: 3.11
Classifier: Programming Language :: Python :: 3.12
Classifier: Programming Language :: Python :: 3.13
Requires-Python: >=3.10
License-File: LICENSE
Requires-Dist: semver>=3.0.4
Requires-Dist: shapely>=2.0.7
Requires-Dist: stactools>=0.4.0
Dynamic: license-file
